setup.py
nil/__init__.py
nil/clean.py
nil.egg-info/PKG-INFO
nil.egg-info/SOURCES.txt
nil.egg-info/dependency_links.txt
nil.egg-info/entry_points.txt
nil.egg-info/not-zip-safe
nil.egg-info/top_level.txt