Metadata-Version: 1.0
Name: nil
Version: 0.1.8
Summary: CMGS cOde ToOls
Home-page: http://hg.cmgs.me/
Author: Kelvin Peng
Author-email: ilskdw@gmail.com
License: MIT
Platform: UNKNOWN
